charboundary/__init__.py
charboundary/constants.py
charboundary/encoders.py
charboundary/features.py
charboundary/models.py
charboundary/onnx_support.py
charboundary/remote_models.py
charboundary/segmenters.py
charboundary/utils.py
charboundary/cli/__init__.py
charboundary/cli/analyze.py
charboundary/cli/best_model.py
charboundary/cli/main.py
charboundary/cli/train.py
charboundary/cli/utils/__init__.py
charboundary/cli/utils/onnx_utils.py
charboundary/resources/__init__.py
charboundary/resources/legal_abbreviations.json
charboundary/resources/small_model.skops.xz
charboundary/resources/onnx/.gitkeep
charboundary/resources/onnx/README.md
charboundary/resources/onnx/__init__.py
charboundary/resources/onnx/small_model.onnx.xz
charboundary/segmenters/__init__.py
charboundary/segmenters/base.py
charboundary/segmenters/evaluation.py
charboundary/segmenters/model_io.py
charboundary/segmenters/paragraphs.py
charboundary/segmenters/sentences.py
charboundary/segmenters/spans.py
charboundary/segmenters/types.py
charboundary-0.5.0.dist-info/licenses/LICENSE
charboundary-0.5.0.dist-info/METADATA
charboundary-0.5.0.dist-info/WHEEL
charboundary-0.5.0.dist-info/entry_points.txt
charboundary-0.5.0.dist-info/top_level.txt
charboundary-0.5.0.dist-info/RECORD
