Metadata-Version: 2.4
Name: charboundary
Version: 0.5.0
Summary: Fast character-based boundary detection for sentence and paragraphs
Author-email: ALEA Institute <hello@aleainstitute.ai>
License-Expression: MIT
Project-URL: Repository, https://github.com/alea-institute/charboundary
Keywords: nlp,text segmentation,sentence boundary detection,paragraph detection,text processing
Classifier: Development Status :: 4 - Beta
Classifier: Intended Audience :: Developers
Classifier: Intended Audience :: Science/Research
Classifier: Programming Language :: Python :: 3
Classifier: Programming Language :: Python :: 3.11
Classifier: Topic :: Scientific/Engineering :: Artificial Intelligence
Classifier: Topic :: Text Processing :: Linguistic
Requires-Python: >=3.11
License-File: LICENSE
Requires-Dist: scikit-learn>=1.3.0
Requires-Dist: tqdm>=4.67.1
Requires-Dist: skops>=0.9.0
Provides-Extra: numpy
Requires-Dist: numpy>=1.23.0; extra == "numpy"
Provides-Extra: onnx
Requires-Dist: onnx>=1.15.0; extra == "onnx"
Requires-Dist: skl2onnx>=1.16.0; extra == "onnx"
Requires-Dist: onnxruntime>=1.16.0; extra == "onnx"
Provides-Extra: dev
Requires-Dist: pytest>=7.0.0; extra == "dev"
Requires-Dist: pytest-benchmark>=4.0.0; extra == "dev"
Requires-Dist: pytest-cov>=4.1.0; extra == "dev"
Requires-Dist: black>=23.0.0; extra == "dev"
Requires-Dist: isort>=5.10.0; extra == "dev"
Requires-Dist: mypy>=1.5.0; extra == "dev"
Dynamic: license-file
